distance_functions-0.1.2.dist-info/METADATA
distance_functions-0.1.2.dist-info/WHEEL
distance_functions/distance_functions.cp311-win_amd64.pyd
distance_functions/distance_functions.cp39-win_amd64.pyd
distance_functions/__init__.py
distance_functions/distance_functions.cp310-win_amd64.pyd
distance_functions-0.1.2.dist-info/RECORD
